nasm/__init__.py
nasm/console.py
nasm/convert.py
nasm-0.1.0.dist-info/DESCRIPTION.rst
nasm-0.1.0.dist-info/METADATA
nasm-0.1.0.dist-info/RECORD
nasm-0.1.0.dist-info/WHEEL
nasm-0.1.0.dist-info/entry_points.txt
nasm-0.1.0.dist-info/metadata.json
nasm-0.1.0.dist-info/top_level.txt
