Metadata-Version: 2.0
Name: nasm
Version: 0.1.0
Summary: A tool for generating 6502 assembly
Home-page: https://github.com/MineRobber9000/nasm
Author: Robert Miles
Author-email: milesrobert374@gmail.com
License: MIT
Keywords: 6502 languages
Platform: UNKNOWN
Classifier: Development Status :: 4 - Beta
Classifier: License :: OSI Approved :: MIT License
Classifier: Programming Language :: Python :: 2
Classifier: Programming Language :: Python :: 2.7
